.flake8
LICENSE
MANIFEST.in
README.md
pyproject.toml
pytest.ini
requirements-dev.txt
requirements.txt
setup.py
docs/Makefile
docs/cover.png
docs/make.bat
docs/requirements.txt
docs/source/conf.py
docs/source/index.rst
docs/source/mknapsack.rst
docs/source/readme.rst
mknapsack/__init__.py
mknapsack/_algos.f
mknapsack/_exceptions.py
mknapsack/_multiple.py
mknapsack/_single.py
mknapsack/_utils.py
mknapsack/_version.py
mknapsack.egg-info/PKG-INFO
mknapsack.egg-info/SOURCES.txt
mknapsack.egg-info/dependency_links.txt
mknapsack.egg-info/requires.txt
mknapsack.egg-info/top_level.txt
tests/__init__.py
tests/test__multiple.py
tests/test__single.py