Metadata-Version: 2.1
Name: mknapsack
Version: 1.1.0
Summary: Solving knapsack and bin packing problems with Python
Author-email: Jesse Myrberg <jesse.myrberg@gmail.com>
License: Copyright (c) 2022 Jesse Myrberg
Project-URL: Homepage, https://github.com/jmyrberg/mknapsack
Project-URL: Documentation, https://mknapsack.readthedocs.io
Keywords: knapsack,bin,packing,optimization
Classifier: Development Status :: 4 - Beta
Classifier: Programming Language :: Python :: 3
Classifier: Intended Audience :: Developers
Classifier: License :: OSI Approved :: MIT License
Requires-Python: <3.12,>=3.8
Provides-Extra: dev
Provides-Extra: docs
License-File: LICENSE
